Metadata-Version: 2.1
Name: odoo12-addon-sale_discount_display_amount
Version: 12.0.1.2.2
Summary: This addon intends to display the amount of the discount computed on sale_order_line and sale_order level
Home-page: https://github.com/OCA/sale-workflow
Author: ACSONE SA/NV,Odoo Community Association (OCA)
Author-email: support@odoo-community.org
License: AGPL-3
Classifier: Programming Language :: Python
Classifier: Framework :: Odoo
Classifier: Framework :: Odoo :: 12.0
Classifier: License :: OSI Approved :: GNU Affero General Public License v3
Requires-Python: >=3.5
Requires-Dist: odoo<12.1dev,>=12.0a
